COPYING
MANIFEST.in
README.md
setup.py
lvmify/__init__.py
lvmify/__main__.py
lvmify.egg-info/PKG-INFO
lvmify.egg-info/SOURCES.txt
lvmify.egg-info/dependency_links.txt
lvmify.egg-info/entry_points.txt
lvmify.egg-info/top_level.txt