Metadata-Version: 1.1
Name: lvmify
Version: 0.0.1
Summary: Convert partitions to LVM
Home-page: https://github.com/g2p/lvmify
Author: Gabriel de Perthuis
Author-email: g2p.code+lvmify@gmail.com
License: GNU GPL
Keywords: lvm partitioning
Platform: UNKNOWN
Classifier: Programming Language :: Python :: 3
Classifier:         License :: OSI Approved :: GNU General Public License (GPL)
Classifier:         Operating System :: POSIX :: Linux
Classifier:         Intended Audience :: System Administrators
Classifier:         Intended Audience :: End Users/Desktop
Classifier:         Topic :: System :: Filesystems
Classifier:         Topic :: Utilities
Classifier:         Environment :: Console
